Metadata-Version: 1.0
Name: lagrange-theorem
Version: 1.3.2
Summary: Decomposition of numbers into the sum of four squares
Home-page: UNKNOWN
Author: Dima Skorobogatov
Author-email: dima.skorobogatov.99@mail.ru
License: UNKNOWN
Platform: UNKNOWN
